secret_santa_bpguasch/__init__.py
secret_santa_bpguasch/algorithm.py
secret_santa_bpguasch/config.py
secret_santa_bpguasch/email.py
secret_santa_bpguasch-1.0.0.dist-info/LICENSE
secret_santa_bpguasch-1.0.0.dist-info/METADATA
secret_santa_bpguasch-1.0.0.dist-info/WHEEL
secret_santa_bpguasch-1.0.0.dist-info/top_level.txt
secret_santa_bpguasch-1.0.0.dist-info/RECORD
