Metadata-Version: 2.1
Name: secret_santa_bpguasch
Version: 1.0.0
Summary: A package that implements the Secret Santa algorithm and notifies participants by email of whom they have to gift.
Author-email: Borja Pérez Guasch <bpguasch@icloud.com>
Project-URL: Homepage, https://github.com/bpguasch/secret-santa
Project-URL: Bug Tracker, https://github.com/bpguasch/secret-santa/issues
Classifier: Programming Language :: Python :: 3
Classifier: License :: OSI Approved :: MIT License
Classifier: Operating System :: OS Independent
Requires-Python: >=3.7
License-File: LICENSE
